fregataa/__init__.py
fregataa/fregataa.py
fregataa-1.0.0.0.dist-info/METADATA
fregataa-1.0.0.0.dist-info/WHEEL
fregataa-1.0.0.0.dist-info/top_level.txt
fregataa-1.0.0.0.dist-info/RECORD
