Metadata-Version: 2.1
Name: fregataa
Version: 1.0.0.0
Summary: To My 
Home-page: https://cho-geonwoo.github.io
Author: cho-geonwoo
Author-email: joungju257@gmail.com
License: MIT
Platform: UNKNOWN
Requires-Python: >=3
